{
  "parent": "minecraft:recipes/root",
  "rewards": {
    "recipes": [
      "embellishcraft:orange_spruce_fancy_bed"
    ]
  },
  "criteria": {
    "has_spruce_planks": {
      "trigger": "minecraft:inventory_changed",
      "conditions": {
        "items": [
          {
            "items": [
              "minecraft:spruce_planks"
            ]
          }
        ]
      }
    },
    "has_the_recipe": {
      "trigger": "minecraft:recipe_unlocked",
      "conditions": {
        "recipe": "embellishcraft:orange_spruce_fancy_bed"
      }
    }
  },
  "requirements": [
    [
      "has_spruce_planks",
      "has_the_recipe"
    ]
  ]
}