{
  "parent": "minecraft:recipes/root",
  "rewards": {
    "recipes": [
      "embellishcraft:paving_stones_wall"
    ]
  },
  "criteria": {
    "has_paving_stones": {
      "trigger": "minecraft:inventory_changed",
      "conditions": {
        "items": [
          {
            "items": [
              "embellishcraft:paving_stones"
            ]
          }
        ]
      }
    },
    "has_the_recipe": {
      "trigger": "minecraft:recipe_unlocked",
      "conditions": {
        "recipe": "embellishcraft:paving_stones_wall"
      }
    }
  },
  "requirements": [
    [
      "has_paving_stones",
      "has_the_recipe"
    ]
  ]
}