{
  "parent": "minecraft:recipes/root",
  "rewards": {
    "recipes": [
      "minecraft:white_concrete_paving_stairs_from_white_concrete_paving_stonecutting"
    ]
  },
  "criteria": {
    "has_white_concrete_paving": {
      "trigger": "minecraft:inventory_changed",
      "conditions": {
        "items": [
          {
            "items": [
              "embellishcraft:white_concrete_paving"
            ]
          }
        ]
      }
    },
    "has_the_recipe": {
      "trigger": "minecraft:recipe_unlocked",
      "conditions": {
        "recipe": "minecraft:white_concrete_paving_stairs_from_white_concrete_paving_stonecutting"
      }
    }
  },
  "requirements": [
    [
      "has_white_concrete_paving",
      "has_the_recipe"
    ]
  ]
}